pyg_sql/__init__.py
pyg_sql/_audit_table.py
pyg_sql/_parse.py
pyg_sql/_sql_table.py
pyg_sql/_sql_writer.py
pyg_sql/_ts_writer.py
pyg_sql-0.0.68.dist-info/LICENSE
pyg_sql-0.0.68.dist-info/METADATA
pyg_sql-0.0.68.dist-info/WHEEL
pyg_sql-0.0.68.dist-info/top_level.txt
pyg_sql-0.0.68.dist-info/RECORD
