Metadata-Version: 2.1
Name: pyg-sql
Version: 0.0.68
Summary: pyg-sql implements a fully-featured no-sql document-store within sql.
Home-page: https://github.com/gityoav/pyg-sql
Author: Yoav Git
Author-email: yoav.git@gmail.com
Project-URL: Bug Tracker, https://github.com/gityoav/pyg-sql/issues
Classifier: Programming Language :: Python :: 3
Classifier: License :: OSI Approved :: GNU General Public License v3 (GPLv3)
Classifier: Operating System :: OS Independent
Requires-Python: >=3.6
License-File: LICENSE
Requires-Dist: pyg-base
Requires-Dist: pyg-encoders
Requires-Dist: sqlalchemy
Requires-Dist: sqlalchemy-utils
